doc2pdf/__init__.py
doc2pdf-0.1.0.dist-info/WHEEL
doc2pdf-0.1.0.dist-info/METADATA
doc2pdf-0.1.0.dist-info/RECORD
